Topsis_VanshikaNassa_102016110/__init__.py
Topsis_VanshikaNassa_102016110/topsis.py
Topsis_Vanshika_102016110/__init__.py
Topsis_Vanshika_102016110/topsis.py
Topsis_VanshikaNassa_102016110-1.2.2.dist-info/LICENSE.txt
Topsis_VanshikaNassa_102016110-1.2.2.dist-info/METADATA
Topsis_VanshikaNassa_102016110-1.2.2.dist-info/WHEEL
Topsis_VanshikaNassa_102016110-1.2.2.dist-info/top_level.txt
Topsis_VanshikaNassa_102016110-1.2.2.dist-info/RECORD
